lawsql_trees/__init__.py
lawsql_trees/codification.py
lawsql_trees/statute.py
lawsql_trees/statute_formatter.py
lawsql_trees/statute_unformatted.py
lawsql_trees-0.0.41.dist-info/WHEEL
lawsql_trees-0.0.41.dist-info/METADATA
lawsql_trees-0.0.41.dist-info/RECORD
