Metadata-Version: 2.1
Name: lawsql-trees
Version: 0.0.41
Summary: Pull and format statute / codification data (tree structures) from local path to raw yaml files.
Author: Marcelino G. Veloso III
Author-email: mars@veloso.one
Requires-Python: >=3.10,<4.0
Classifier: Programming Language :: Python :: 3
Classifier: Programming Language :: Python :: 3.10
Requires-Dist: Markdown (>=3.3.7,<4.0.0)
Requires-Dist: beautifulsoup4 (>=4.11.1,<5.0.0)
Requires-Dist: citation-decision (>=0.0.6,<0.0.7)
Requires-Dist: html5lib (>=1.1,<2.0)
Requires-Dist: python-slugify (>=6.1.2,<7.0.0)
Requires-Dist: sqlite-utils (>=3.26,<4.0)
Requires-Dist: statute-utils (>=0.0.2,<0.0.3)
Requires-Dist: treeish (>=0.0.2,<0.0.3)
